airduct/__init__.py
airduct/api/__init__.py
airduct/api/api.py
airduct/cli/__init__.py
airduct/cli/run.py
airduct/config.py
airduct/core.py
airduct/database.py
airduct/flowfinder.py
airduct/logger.py
airduct-0.1.22.dist-info/entry_points.txt
airduct-0.1.22.dist-info/WHEEL
airduct-0.1.22.dist-info/METADATA
airduct-0.1.22.dist-info/RECORD
